word_counter_AI/__init__.py
word_counter_AI/count_words.py
word_counter_AI-1.0.1.dist-info/LICENSE
word_counter_AI-1.0.1.dist-info/METADATA
word_counter_AI-1.0.1.dist-info/WHEEL
word_counter_AI-1.0.1.dist-info/top_level.txt
word_counter_AI-1.0.1.dist-info/RECORD
