Metadata-Version: 2.1
Name: word-counter-AI
Version: 1.0.1
Summary: AI word counter package
Author-email: wojpo <ilikeahottodogu@gmail.com>
Project-URL: Homepage, https://github.com/wojpo/word-counter-AI/
Project-URL: Issues, https://github.com/wojpo/word-counter-AI/issues
Classifier: Programming Language :: Python :: 3
Classifier: License :: OSI Approved :: MIT License
Classifier: Operating System :: OS Independent
Requires-Python: >=3.9
License-File: LICENSE
Requires-Dist: google-generativeai
